[
  {
    "CustomerName": "Innovar S.A.",
    "From": "Av. Corrientes 1234, CABA",
    "To": "Av. San Martín 1300, CABA",
    "Description": "Servicio de transporte para Innovar S.A.",
    "ScheduledDate": "2025-02-21T00:00:00"
  },
  {
    "CustomerName": "Alimentos del Sol",
    "From": "Av. Santa Fe 567, CABA",
    "To": "Calle Juramento 142, CABA",
    "Description": "Servicio de transporte para Alimentos del Sol",
    "ScheduledDate": "2025-02-24T00:00:00"
  },
  {
    "CustomerName": "Constructora Aurora",
    "From": "Av. Callao 890, CABA",
    "To": "Av. Corrientes 2500, CABA",
    "Description": "Servicio de transporte para Constructora Aurora",
    "ScheduledDate": "2025-02-25T00:00:00"
  },
  {
    "CustomerName": "Inversiones Delta",
    "From": "Av. Rivadavia 2345, CABA",
    "To": "Calle Bolívar 360, CABA",
    "Description": "Servicio de transporte para Inversiones Delta",
    "ScheduledDate": "2025-02-26T00:00:00"
  },
  {
    "CustomerName": "Tecnologías Andes",
    "From": "Av. 9 de Julio 101, CABA",
    "To": "Av. Callao 470, CABA",
    "Description": "Servicio de transporte para Tecnologías Andes",
    "ScheduledDate": "2025-02-27T00:00:00"
  },
  {
    "CustomerName": "Consultora Montaña",
    "From": "Av. Pueyrredón 456, CABA",
    "To": "Calle Florida 580, CABA",
    "Description": "Servicio de transporte para Consultora Montaña",
    "ScheduledDate": "2025-02-28T00:00:00"
  },
  {
    "CustomerName": "Financiera Capital",
    "From": "Calle Florida 789, CABA",
    "To": "Av. Rivadavia 690, CABA",
    "Description": "Servicio de transporte para Financiera Capital",
    "ScheduledDate": "2025-03-03T00:00:00"
  },
  {
    "CustomerName": "Sistemas Urbanos",
    "From": "Av. del Libertador 321, CABA",
    "To": "Calle 9 de Julio 800, CABA",
    "Description": "Servicio de transporte para Sistemas Urbanos",
    "ScheduledDate": "2025-03-04T00:00:00"
  },
  {
    "CustomerName": "Seguros del Plata",
    "From": "Av. de Mayo 654, CABA",
    "To": "Av. Pueyrredón 910, CABA",
    "Description": "Servicio de transporte para Seguros del Plata",
    "ScheduledDate": "2025-03-05T00:00:00"
  },
  {
    "CustomerName": "Edificaciones Modernas",
    "From": "Av. Cerviño 987, CABA",
    "To": "Calle Tucumán 102, CABA",
    "Description": "Servicio de transporte para Edificaciones Modernas",
    "ScheduledDate": "2025-03-06T00:00:00"
  },
  {
    "CustomerName": "Vivero Tropical",
    "From": "Av. San Martín 112, CABA",
    "To": "Av. Santa Fe 113, CABA",
    "Description": "Servicio de transporte para Vivero Tropical",
    "ScheduledDate": "2025-03-07T00:00:00"
  },
  {
    "CustomerName": "Productos Naturales",
    "From": "Calle Perú 334, CABA",
    "To": "Calle de la República 124, CABA",
    "Description": "Servicio de transporte para Productos Naturales",
    "ScheduledDate": "2025-03-10T00:00:00"
  },
  {
    "CustomerName": "Grupo Sideral",
    "From": "Av. Belgrano 556, CABA",
    "To": "Av. de Mayo 235, CABA",
    "Description": "Servicio de transporte para Grupo Sideral",
    "ScheduledDate": "2025-03-11T00:00:00"
  },
  {
    "CustomerName": "Optima Salud",
    "From": "Calle Sarmiento 778, CABA",
    "To": "Calle Esmeralda 346, CABA",
    "Description": "Servicio de transporte para Optima Salud",
    "ScheduledDate": "2025-03-12T00:00:00"
  },
  {
    "CustomerName": "Energía Renovable",
    "From": "Av. Independencia 990, CABA",
    "To": "Av. Libertador 457, CABA",
    "Description": "Servicio de transporte para Energía Renovable",
    "ScheduledDate": "2025-03-13T00:00:00"
  },
  {
    "CustomerName": "Futuro Digital",
    "From": "Calle Bolívar 221, CABA",
    "To": "Calle Belgrano 568, CABA",
    "Description": "Servicio de transporte para Futuro Digital",
    "ScheduledDate": "2025-03-14T00:00:00"
  },
  {
    "CustomerName": "Mundo Verde",
    "From": "Av. Entre Ríos 443, CABA",
    "To": "Av. del Libertador 679, CABA",
    "Description": "Servicio de transporte para Mundo Verde",
    "ScheduledDate": "2025-03-17T00:00:00"
  },
  {
    "CustomerName": "Artesanía Criolla",
    "From": "Av. Lavalle 665, CABA",
    "To": "Calle Alsina 780, CABA",
    "Description": "Servicio de transporte para Artesanía Criolla",
    "ScheduledDate": "2025-03-18T00:00:00"
  },
  {
    "CustomerName": "Estilo y Diseño",
    "From": "Calle Moreno 887, CABA",
    "To": "Av. Congreso 891, CABA",
    "Description": "Servicio de transporte para Estilo y Diseño",
    "ScheduledDate": "2025-03-19T00:00:00"
  },
  {
    "CustomerName": "Cultura Viva",
    "From": "Av. Maipú 109, CABA",
    "To": "Calle San Juan 902, CABA",
    "Description": "Servicio de transporte para Cultura Viva",
    "ScheduledDate": "2025-03-20T00:00:00"
  },
  {
    "CustomerName": "Vanguardia Empresarial",
    "From": "Calle Tucumán 312, CABA",
    "To": "Av. Maipú 103, CABA",
    "Description": "Servicio de transporte para Vanguardia Empresarial",
    "ScheduledDate": "2025-03-21T00:00:00"
  },
  {
    "CustomerName": "Nexo Innovación",
    "From": "Av. Congreso 534, CABA",
    "To": "Calle San Lorenzo 214, CABA",
    "Description": "Servicio de transporte para Nexo Innovación",
    "ScheduledDate": "2025-02-21T00:00:00"
  },
  {
    "CustomerName": "Soluciones Integrales",
    "From": "Calle Alsina 756, CABA",
    "To": "Av. General Paz 325, CABA",
    "Description": "Servicio de transporte para Soluciones Integrales",
    "ScheduledDate": "2025-02-24T00:00:00"
  },
  {
    "CustomerName": "Horizonte Financiero",
    "From": "Av. de los Incas 978, CABA",
    "To": "Calle Dorrego 436, CABA",
    "Description": "Servicio de transporte para Horizonte Financiero",
    "ScheduledDate": "2025-02-25T00:00:00"
  },
  {
    "CustomerName": "Impulso Creativo",
    "From": "Calle San Juan 190, CABA",
    "To": "Av. Lavalle 547, CABA",
    "Description": "Servicio de transporte para Impulso Creativo",
    "ScheduledDate": "2025-02-26T00:00:00"
  },
  {
    "CustomerName": "Red Empresarial",
    "From": "Av. Roca 212, CABA",
    "To": "Calle Mitre 658, CABA",
    "Description": "Servicio de transporte para Red Empresarial",
    "ScheduledDate": "2025-02-27T00:00:00"
  },
  {
    "CustomerName": "Natura Organics",
    "From": "Calle 25 de Mayo 234, CABA",
    "To": "Av. Córdoba 769, CABA",
    "Description": "Servicio de transporte para Natura Organics",
    "ScheduledDate": "2025-02-28T00:00:00"
  },
  {
    "CustomerName": "Calidad Premium",
    "From": "Av. Juan B. Justo 456, CABA",
    "To": "Calle Independencia 880, CABA",
    "Description": "Servicio de transporte para Calidad Premium",
    "ScheduledDate": "2025-03-03T00:00:00"
  },
  {
    "CustomerName": "EcoVida",
    "From": "Calle Esmeralda 678, CABA",
    "To": "Av. Entre Ríos 991, CABA",
    "Description": "Servicio de transporte para EcoVida",
    "ScheduledDate": "2025-03-04T00:00:00"
  },
  {
    "CustomerName": "Gourmet Delicias",
    "From": "Av. General Paz 890, CABA",
    "To": "Calle Sarmiento 102, CABA",
    "Description": "Servicio de transporte para Gourmet Delicias",
    "ScheduledDate": "2025-03-05T00:00:00"
  },
  {
    "CustomerName": "Sabor y Tradición",
    "From": "Calle San Lorenzo 101, CABA",
    "To": "Av. 25 de Mayo 213, CABA",
    "Description": "Servicio de transporte para Sabor y Tradición",
    "ScheduledDate": "2025-03-06T00:00:00"
  },
  {
    "CustomerName": "Cine & Arte",
    "From": "Av. Paseo Colón 202, CABA",
    "To": "Calle Roque Sáenz Peña 324, CABA",
    "Description": "Servicio de transporte para Cine & Arte",
    "ScheduledDate": "2025-03-07T00:00:00"
  },
  {
    "CustomerName": "Música Latina",
    "From": "Calle Dorrego 303, CABA",
    "To": "Av. Juan B. Justo 435, CABA",
    "Description": "Servicio de transporte para Música Latina",
    "ScheduledDate": "2025-03-10T00:00:00"
  },
  {
    "CustomerName": "Estudios Arco",
    "From": "Av. Córdoba 404, CABA",
    "To": "Calle Corrientes 546, CABA",
    "Description": "Servicio de transporte para Estudios Arco",
    "ScheduledDate": "2025-03-11T00:00:00"
  },
  {
    "CustomerName": "MediaFusión",
    "From": "Calle Mitre 505, CABA",
    "To": "Av. Santa Fe 657, CABA",
    "Description": "Servicio de transporte para MediaFusión",
    "ScheduledDate": "2025-03-12T00:00:00"
  },
  {
    "CustomerName": "Tecnova",
    "From": "Av. Belgrano 606, CABA",
    "To": "Calle Callao 768, CABA",
    "Description": "Servicio de transporte para Tecnova",
    "ScheduledDate": "2025-03-13T00:00:00"
  },
  {
    "CustomerName": "Pixel Creativo",
    "From": "Calle Lavalle 707, CABA",
    "To": "Av. Roca 879, CABA",
    "Description": "Servicio de transporte para Pixel Creativo",
    "ScheduledDate": "2025-03-14T00:00:00"
  },
  {
    "CustomerName": "Digital Minds",
    "From": "Av. Roque Sáenz Peña 808, CABA",
    "To": "Calle Belgrano 980, CABA",
    "Description": "Servicio de transporte para Digital Minds",
    "ScheduledDate": "2025-03-17T00:00:00"
  },
  {
    "CustomerName": "DataWave",
    "From": "Av. Corrientes 1234, CABA",
    "To": "Av. San Martín 1300, CABA",
    "Description": "Servicio de transporte para DataWave",
    "ScheduledDate": "2025-03-18T00:00:00"
  },
  {
    "CustomerName": "InfoTech Solutions",
    "From": "Av. Santa Fe 567, CABA",
    "To": "Calle Juramento 142, CABA",
    "Description": "Servicio de transporte para InfoTech Solutions",
    "ScheduledDate": "2025-03-19T00:00:00"
  },
  {
    "CustomerName": "Innovación Global",
    "From": "Av. Callao 890, CABA",
    "To": "Av. Corrientes 2500, CABA",
    "Description": "Servicio de transporte para Innovación Global",
    "ScheduledDate": "2025-03-20T00:00:00"
  },
  {
    "CustomerName": "Smart Business",
    "From": "Av. Rivadavia 2345, CABA",
    "To": "Calle Bolívar 360, CABA",
    "Description": "Servicio de transporte para Smart Business",
    "ScheduledDate": "2025-03-21T00:00:00"
  },
  {
    "CustomerName": "Alpha Invest",
    "From": "Av. 9 de Julio 101, CABA",
    "To": "Av. Callao 470, CABA",
    "Description": "Servicio de transporte para Alpha Invest",
    "ScheduledDate": "2025-02-21T00:00:00"
  },
  {
    "CustomerName": "Beta Corp",
    "From": "Av. Pueyrredón 456, CABA",
    "To": "Calle Florida 580, CABA",
    "Description": "Servicio de transporte para Beta Corp",
    "ScheduledDate": "2025-02-24T00:00:00"
  },
  {
    "CustomerName": "Gamma Holdings",
    "From": "Calle Florida 789, CABA",
    "To": "Av. Rivadavia 690, CABA",
    "Description": "Servicio de transporte para Gamma Holdings",
    "ScheduledDate": "2025-02-25T00:00:00"
  },
  {
    "CustomerName": "Omega Industries",
    "From": "Av. del Libertador 321, CABA",
    "To": "Calle 9 de Julio 800, CABA",
    "Description": "Servicio de transporte para Omega Industries",
    "ScheduledDate": "2025-02-26T00:00:00"
  },
  {
    "CustomerName": "Sigma Enterprises",
    "From": "Av. de Mayo 654, CABA",
    "To": "Av. Pueyrredón 910, CABA",
    "Description": "Servicio de transporte para Sigma Enterprises",
    "ScheduledDate": "2025-02-27T00:00:00"
  },
  {
    "CustomerName": "Delta Services",
    "From": "Av. Cerviño 987, CABA",
    "To": "Calle Tucumán 102, CABA",
    "Description": "Servicio de transporte para Delta Services",
    "ScheduledDate": "2025-02-28T00:00:00"
  },
  {
    "CustomerName": "Epsilon Group",
    "From": "Av. San Martín 112, CABA",
    "To": "Av. Santa Fe 113, CABA",
    "Description": "Servicio de transporte para Epsilon Group",
    "ScheduledDate": "2025-03-03T00:00:00"
  },
  {
    "CustomerName": "Zeta Solutions",
    "From": "Calle Perú 334, CABA",
    "To": "Calle de la República 124, CABA",
    "Description": "Servicio de transporte para Zeta Solutions",
    "ScheduledDate": "2025-03-04T00:00:00"
  },
  {
    "CustomerName": "Kappa Consulting",
    "From": "Av. Belgrano 556, CABA",
    "To": "Av. de Mayo 235, CABA",
    "Description": "Servicio de transporte para Kappa Consulting",
    "ScheduledDate": "2025-03-05T00:00:00"
  },
  {
    "CustomerName": "Lambda Ventures",
    "From": "Calle Sarmiento 778, CABA",
    "To": "Calle Esmeralda 346, CABA",
    "Description": "Servicio de transporte para Lambda Ventures",
    "ScheduledDate": "2025-03-06T00:00:00"
  },
  {
    "CustomerName": "Nu Capital",
    "From": "Av. Independencia 990, CABA",
    "To": "Av. Libertador 457, CABA",
    "Description": "Servicio de transporte para Nu Capital",
    "ScheduledDate": "2025-03-07T00:00:00"
  },
  {
    "CustomerName": "Omicron Technologies",
    "From": "Calle Bolívar 221, CABA",
    "To": "Calle Belgrano 568, CABA",
    "Description": "Servicio de transporte para Omicron Technologies",
    "ScheduledDate": "2025-03-10T00:00:00"
  },
  {
    "CustomerName": "Pi Electronics",
    "From": "Av. Entre Ríos 443, CABA",
    "To": "Av. del Libertador 679, CABA",
    "Description": "Servicio de transporte para Pi Electronics",
    "ScheduledDate": "2025-03-11T00:00:00"
  },
  {
    "CustomerName": "Rho Retail",
    "From": "Av. Lavalle 665, CABA",
    "To": "Calle Alsina 780, CABA",
    "Description": "Servicio de transporte para Rho Retail",
    "ScheduledDate": "2025-03-12T00:00:00"
  },
  {
    "CustomerName": "Tau Foods",
    "From": "Calle Moreno 887, CABA",
    "To": "Av. Congreso 891, CABA",
    "Description": "Servicio de transporte para Tau Foods",
    "ScheduledDate": "2025-03-13T00:00:00"
  },
  {
    "CustomerName": "Upsilon Pharma",
    "From": "Av. Maipú 109, CABA",
    "To": "Calle San Juan 902, CABA",
    "Description": "Servicio de transporte para Upsilon Pharma",
    "ScheduledDate": "2025-03-14T00:00:00"
  },
  {
    "CustomerName": "Phi Beverages",
    "From": "Calle Tucumán 312, CABA",
    "To": "Av. Maipú 103, CABA",
    "Description": "Servicio de transporte para Phi Beverages",
    "ScheduledDate": "2025-03-17T00:00:00"
  },
  {
    "CustomerName": "Chi Textiles",
    "From": "Av. Congreso 534, CABA",
    "To": "Calle San Lorenzo 214, CABA",
    "Description": "Servicio de transporte para Chi Textiles",
    "ScheduledDate": "2025-03-18T00:00:00"
  },
  {
    "CustomerName": "Psi Chemicals",
    "From": "Calle Alsina 756, CABA",
    "To": "Av. General Paz 325, CABA",
    "Description": "Servicio de transporte para Psi Chemicals",
    "ScheduledDate": "2025-03-19T00:00:00"
  },
  {
    "CustomerName": "Omega Materials",
    "From": "Av. de los Incas 978, CABA",
    "To": "Calle Dorrego 436, CABA",
    "Description": "Servicio de transporte para Omega Materials",
    "ScheduledDate": "2025-03-20T00:00:00"
  },
  {
    "CustomerName": "Nueva Imagen",
    "From": "Calle San Juan 190, CABA",
    "To": "Av. Lavalle 547, CABA",
    "Description": "Servicio de transporte para Nueva Imagen",
    "ScheduledDate": "2025-03-21T00:00:00"
  },
  {
    "CustomerName": "Brillante Ideas",
    "From": "Av. Roca 212, CABA",
    "To": "Calle Mitre 658, CABA",
    "Description": "Servicio de transporte para Brillante Ideas",
    "ScheduledDate": "2025-02-21T00:00:00"
  },
  {
    "CustomerName": "Cumbre Creativa",
    "From": "Calle 25 de Mayo 234, CABA",
    "To": "Av. Córdoba 769, CABA",
    "Description": "Servicio de transporte para Cumbre Creativa",
    "ScheduledDate": "2025-02-24T00:00:00"
  },
  {
    "CustomerName": "Faro Empresarial",
    "From": "Av. Juan B. Justo 456, CABA",
    "To": "Calle Independencia 880, CABA",
    "Description": "Servicio de transporte para Faro Empresarial",
    "ScheduledDate": "2025-02-25T00:00:00"
  },
  {
    "CustomerName": "Punto de Encuentro",
    "From": "Calle Esmeralda 678, CABA",
    "To": "Av. Entre Ríos 991, CABA",
    "Description": "Servicio de transporte para Punto de Encuentro",
    "ScheduledDate": "2025-02-26T00:00:00"
  },
  {
    "CustomerName": "Clave Urbana",
    "From": "Av. General Paz 890, CABA",
    "To": "Calle Sarmiento 102, CABA",
    "Description": "Servicio de transporte para Clave Urbana",
    "ScheduledDate": "2025-02-27T00:00:00"
  },
  {
    "CustomerName": "Estrella del Norte",
    "From": "Calle San Lorenzo 101, CABA",
    "To": "Av. 25 de Mayo 213, CABA",
    "Description": "Servicio de transporte para Estrella del Norte",
    "ScheduledDate": "2025-02-28T00:00:00"
  },
  {
    "CustomerName": "Aurora Global",
    "From": "Av. Paseo Colón 202, CABA",
    "To": "Calle Roque Sáenz Peña 324, CABA",
    "Description": "Servicio de transporte para Aurora Global",
    "ScheduledDate": "2025-03-03T00:00:00"
  },
  {
    "CustomerName": "Sol Naciente",
    "From": "Calle Dorrego 303, CABA",
    "To": "Av. Juan B. Justo 435, CABA",
    "Description": "Servicio de transporte para Sol Naciente",
    "ScheduledDate": "2025-03-04T00:00:00"
  },
  {
    "CustomerName": "Luz de Plata",
    "From": "Av. Córdoba 404, CABA",
    "To": "Calle Corrientes 546, CABA",
    "Description": "Servicio de transporte para Luz de Plata",
    "ScheduledDate": "2025-03-05T00:00:00"
  },
  {
    "CustomerName": "Manantial Natural",
    "From": "Calle Mitre 505, CABA",
    "To": "Av. Santa Fe 657, CABA",
    "Description": "Servicio de transporte para Manantial Natural",
    "ScheduledDate": "2025-03-06T00:00:00"
  },
  {
    "CustomerName": "Fuente de Vida",
    "From": "Av. Belgrano 606, CABA",
    "To": "Calle Callao 768, CABA",
    "Description": "Servicio de transporte para Fuente de Vida",
    "ScheduledDate": "2025-03-07T00:00:00"
  },
  {
    "CustomerName": "Corazón Argentino",
    "From": "Calle Lavalle 707, CABA",
    "To": "Av. Roca 879, CABA",
    "Description": "Servicio de transporte para Corazón Argentino",
    "ScheduledDate": "2025-03-10T00:00:00"
  },
  {
    "CustomerName": "Patrimonio Vivo",
    "From": "Av. Roque Sáenz Peña 808, CABA",
    "To": "Calle Belgrano 980, CABA",
    "Description": "Servicio de transporte para Patrimonio Vivo",
    "ScheduledDate": "2025-03-11T00:00:00"
  },
  {
    "CustomerName": "Raíces y Alas",
    "From": "Av. Corrientes 1234, CABA",
    "To": "Av. San Martín 1300, CABA",
    "Description": "Servicio de transporte para Raíces y Alas",
    "ScheduledDate": "2025-03-12T00:00:00"
  },
  {
    "CustomerName": "Sueño Dorado",
    "From": "Av. Santa Fe 567, CABA",
    "To": "Calle Juramento 142, CABA",
    "Description": "Servicio de transporte para Sueño Dorado",
    "ScheduledDate": "2025-03-13T00:00:00"
  },
  {
    "CustomerName": "Horizonte Claro",
    "From": "Av. Callao 890, CABA",
    "To": "Av. Corrientes 2500, CABA",
    "Description": "Servicio de transporte para Horizonte Claro",
    "ScheduledDate": "2025-03-14T00:00:00"
  },
  {
    "CustomerName": "Visión Serena",
    "From": "Av. Rivadavia 2345, CABA",
    "To": "Calle Bolívar 360, CABA",
    "Description": "Servicio de transporte para Visión Serena",
    "ScheduledDate": "2025-03-17T00:00:00"
  },
  {
    "CustomerName": "Imaginarium",
    "From": "Av. 9 de Julio 101, CABA",
    "To": "Av. Callao 470, CABA",
    "Description": "Servicio de transporte para Imaginarium",
    "ScheduledDate": "2025-03-18T00:00:00"
  },
  {
    "CustomerName": "Ideas Frescas",
    "From": "Av. Pueyrredón 456, CABA",
    "To": "Calle Florida 580, CABA",
    "Description": "Servicio de transporte para Ideas Frescas",
    "ScheduledDate": "2025-03-19T00:00:00"
  },
  {
    "CustomerName": "Espacio Innovador",
    "From": "Calle Florida 789, CABA",
    "To": "Av. Rivadavia 690, CABA",
    "Description": "Servicio de transporte para Espacio Innovador",
    "ScheduledDate": "2025-03-20T00:00:00"
  },
  {
    "CustomerName": "Planeta Verde",
    "From": "Av. del Libertador 321, CABA",
    "To": "Calle 9 de Julio 800, CABA",
    "Description": "Servicio de transporte para Planeta Verde",
    "ScheduledDate": "2025-03-21T00:00:00"
  },
  {
    "CustomerName": "Marea Alta",
    "From": "Av. de Mayo 654, CABA",
    "To": "Av. Pueyrredón 910, CABA",
    "Description": "Servicio de transporte para Marea Alta",
    "ScheduledDate": "2025-02-21T00:00:00"
  },
  {
    "CustomerName": "Río Claro",
    "From": "Av. Cerviño 987, CABA",
    "To": "Calle Tucumán 102, CABA",
    "Description": "Servicio de transporte para Río Claro",
    "ScheduledDate": "2025-02-24T00:00:00"
  },
  {
    "CustomerName": "Lago Azul",
    "From": "Av. San Martín 112, CABA",
    "To": "Av. Santa Fe 113, CABA",
    "Description": "Servicio de transporte para Lago Azul",
    "ScheduledDate": "2025-02-25T00:00:00"
  },
  {
    "CustomerName": "Valle Encantado",
    "From": "Calle Perú 334, CABA",
    "To": "Calle de la República 124, CABA",
    "Description": "Servicio de transporte para Valle Encantado",
    "ScheduledDate": "2025-02-26T00:00:00"
  },
  {
    "CustomerName": "Cumbre Andina",
    "From": "Av. Belgrano 556, CABA",
    "To": "Av. de Mayo 235, CABA",
    "Description": "Servicio de transporte para Cumbre Andina",
    "ScheduledDate": "2025-02-27T00:00:00"
  },
  {
    "CustomerName": "Pampa Serena",
    "From": "Calle Sarmiento 778, CABA",
    "To": "Calle Esmeralda 346, CABA",
    "Description": "Servicio de transporte para Pampa Serena",
    "ScheduledDate": "2025-02-28T00:00:00"
  },
  {
    "CustomerName": "Sol y Sombra",
    "From": "Av. Independencia 990, CABA",
    "To": "Av. Libertador 457, CABA",
    "Description": "Servicio de transporte para Sol y Sombra",
    "ScheduledDate": "2025-03-03T00:00:00"
  },
  {
    "CustomerName": "Luz y Vida",
    "From": "Calle Bolívar 221, CABA",
    "To": "Calle Belgrano 568, CABA",
    "Description": "Servicio de transporte para Luz y Vida",
    "ScheduledDate": "2025-03-04T00:00:00"
  },
  {
    "CustomerName": "Amanecer Dorado",
    "From": "Av. Entre Ríos 443, CABA",
    "To": "Av. del Libertador 679, CABA",
    "Description": "Servicio de transporte para Amanecer Dorado",
    "ScheduledDate": "2025-03-05T00:00:00"
  },
  {
    "CustomerName": "Reflejo Urbano",
    "From": "Av. Lavalle 665, CABA",
    "To": "Calle Alsina 780, CABA",
    "Description": "Servicio de transporte para Reflejo Urbano",
    "ScheduledDate": "2025-03-06T00:00:00"
  },
  {
    "CustomerName": "Punto Focal",
    "From": "Calle Moreno 887, CABA",
    "To": "Av. Congreso 891, CABA",
    "Description": "Servicio de transporte para Punto Focal",
    "ScheduledDate": "2025-03-07T00:00:00"
  },
  {
    "CustomerName": "Núcleo Creativo",
    "From": "Av. Maipú 109, CABA",
    "To": "Calle San Juan 902, CABA",
    "Description": "Servicio de transporte para Núcleo Creativo",
    "ScheduledDate": "2025-03-10T00:00:00"
  },
  {
    "CustomerName": "Mente Brillante",
    "From": "Calle Tucumán 312, CABA",
    "To": "Av. Maipú 103, CABA",
    "Description": "Servicio de transporte para Mente Brillante",
    "ScheduledDate": "2025-03-11T00:00:00"
  },
  {
    "CustomerName": "Esencia Pura",
    "From": "Av. Congreso 534, CABA",
    "To": "Calle San Lorenzo 214, CABA",
    "Description": "Servicio de transporte para Esencia Pura",
    "ScheduledDate": "2025-03-12T00:00:00"
  },
  {
    "CustomerName": "Sabor Natural",
    "From": "Calle Alsina 756, CABA",
    "To": "Av. General Paz 325, CABA",
    "Description": "Servicio de transporte para Sabor Natural",
    "ScheduledDate": "2025-03-13T00:00:00"
  },
  {
    "CustomerName": "Delicias del Campo",
    "From": "Av. de los Incas 978, CABA",
    "To": "Calle Dorrego 436, CABA",
    "Description": "Servicio de transporte para Delicias del Campo",
    "ScheduledDate": "2025-03-14T00:00:00"
  },
  {
    "CustomerName": "Sabores del Valle",
    "From": "Calle San Juan 190, CABA",
    "To": "Av. Lavalle 547, CABA",
    "Description": "Servicio de transporte para Sabores del Valle",
    "ScheduledDate": "2025-03-17T00:00:00"
  },
  {
    "CustomerName": "Frescura Extrema",
    "From": "Av. Roca 212, CABA",
    "To": "Calle Mitre 658, CABA",
    "Description": "Servicio de transporte para Frescura Extrema",
    "ScheduledDate": "2025-03-18T00:00:00"
  },
  {
    "CustomerName": "Cosecha Dorada",
    "From": "Calle 25 de Mayo 234, CABA",
    "To": "Av. Córdoba 769, CABA",
    "Description": "Servicio de transporte para Cosecha Dorada",
    "ScheduledDate": "2025-03-19T00:00:00"
  },
  {
    "CustomerName": "Verde Vivo",
    "From": "Av. Juan B. Justo 456, CABA",
    "To": "Calle Independencia 880, CABA",
    "Description": "Servicio de transporte para Verde Vivo",
    "ScheduledDate": "2025-03-20T00:00:00"
  },
  {
    "CustomerName": "AgroPlus",
    "From": "Calle Esmeralda 678, CABA",
    "To": "Av. Entre Ríos 991, CABA",
    "Description": "Servicio de transporte para AgroPlus",
    "ScheduledDate": "2025-03-21T00:00:00"
  },
  {
    "CustomerName": "Frutos del Sur",
    "From": "Av. General Paz 890, CABA",
    "To": "Calle Sarmiento 102, CABA",
    "Description": "Servicio de transporte para Frutos del Sur",
    "ScheduledDate": "2025-02-21T00:00:00"
  },
  {
    "CustomerName": "Natura Organix",
    "From": "Calle San Lorenzo 101, CABA",
    "To": "Av. 25 de Mayo 213, CABA",
    "Description": "Servicio de transporte para Natura Organix",
    "ScheduledDate": "2025-02-24T00:00:00"
  },
  {
    "CustomerName": "Cultiva Bien",
    "From": "Av. Paseo Colón 202, CABA",
    "To": "Calle Roque Sáenz Peña 324, CABA",
    "Description": "Servicio de transporte para Cultiva Bien",
    "ScheduledDate": "2025-02-25T00:00:00"
  },
  {
    "CustomerName": "Finca Real",
    "From": "Calle Dorrego 303, CABA",
    "To": "Av. Juan B. Justo 435, CABA",
    "Description": "Servicio de transporte para Finca Real",
    "ScheduledDate": "2025-02-26T00:00:00"
  },
  {
    "CustomerName": "Granja del Sol",
    "From": "Av. Córdoba 404, CABA",
    "To": "Calle Corrientes 546, CABA",
    "Description": "Servicio de transporte para Granja del Sol",
    "ScheduledDate": "2025-02-27T00:00:00"
  },
  {
    "CustomerName": "Cosecha Selecta",
    "From": "Calle Mitre 505, CABA",
    "To": "Av. Santa Fe 657, CABA",
    "Description": "Servicio de transporte para Cosecha Selecta",
    "ScheduledDate": "2025-02-28T00:00:00"
  },
  {
    "CustomerName": "Campo Unido",
    "From": "Av. Belgrano 606, CABA",
    "To": "Calle Callao 768, CABA",
    "Description": "Servicio de transporte para Campo Unido",
    "ScheduledDate": "2025-03-03T00:00:00"
  },
  {
    "CustomerName": "Frescura Natural",
    "From": "Calle Lavalle 707, CABA",
    "To": "Av. Roca 879, CABA",
    "Description": "Servicio de transporte para Frescura Natural",
    "ScheduledDate": "2025-03-04T00:00:00"
  },
  {
    "CustomerName": "Vitamina S.A.",
    "From": "Av. Roque Sáenz Peña 808, CABA",
    "To": "Calle Belgrano 980, CABA",
    "Description": "Servicio de transporte para Vitamina S.A.",
    "ScheduledDate": "2025-03-05T00:00:00"
  },
  {
    "CustomerName": "Sabor y Vida",
    "From": "Av. Corrientes 1234, CABA",
    "To": "Av. San Martín 1300, CABA",
    "Description": "Servicio de transporte para Sabor y Vida",
    "ScheduledDate": "2025-03-06T00:00:00"
  },
  {
    "CustomerName": "Fusión Creativa",
    "From": "Av. Santa Fe 567, CABA",
    "To": "Calle Juramento 142, CABA",
    "Description": "Servicio de transporte para Fusión Creativa",
    "ScheduledDate": "2025-03-07T00:00:00"
  },
  {
    "CustomerName": "Armonía Global",
    "From": "Av. Callao 890, CABA",
    "To": "Av. Corrientes 2500, CABA",
    "Description": "Servicio de transporte para Armonía Global",
    "ScheduledDate": "2025-03-10T00:00:00"
  },
  {
    "CustomerName": "Ritmo Urbano",
    "From": "Av. Rivadavia 2345, CABA",
    "To": "Calle Bolívar 360, CABA",
    "Description": "Servicio de transporte para Ritmo Urbano",
    "ScheduledDate": "2025-03-11T00:00:00"
  },
  {
    "CustomerName": "Expreso Digital",
    "From": "Av. 9 de Julio 101, CABA",
    "To": "Av. Callao 470, CABA",
    "Description": "Servicio de transporte para Expreso Digital",
    "ScheduledDate": "2025-03-12T00:00:00"
  },
  {
    "CustomerName": "Eco Inteligente",
    "From": "Av. Pueyrredón 456, CABA",
    "To": "Calle Florida 580, CABA",
    "Description": "Servicio de transporte para Eco Inteligente",
    "ScheduledDate": "2025-03-13T00:00:00"
  },
  {
    "CustomerName": "EcoSustentable",
    "From": "Calle Florida 789, CABA",
    "To": "Av. Rivadavia 690, CABA",
    "Description": "Servicio de transporte para EcoSustentable",
    "ScheduledDate": "2025-03-14T00:00:00"
  },
  {
    "CustomerName": "Verde Futuro",
    "From": "Av. del Libertador 321, CABA",
    "To": "Calle 9 de Julio 800, CABA",
    "Description": "Servicio de transporte para Verde Futuro",
    "ScheduledDate": "2025-03-17T00:00:00"
  },
  {
    "CustomerName": "Innovar Plus",
    "From": "Av. de Mayo 654, CABA",
    "To": "Av. Pueyrredón 910, CABA",
    "Description": "Servicio de transporte para Innovar Plus",
    "ScheduledDate": "2025-03-18T00:00:00"
  },
  {
    "CustomerName": "Clima Perfecto",
    "From": "Av. Cerviño 987, CABA",
    "To": "Calle Tucumán 102, CABA",
    "Description": "Servicio de transporte para Clima Perfecto",
    "ScheduledDate": "2025-03-19T00:00:00"
  },
  {
    "CustomerName": "Hogar Dulce Hogar",
    "From": "Av. San Martín 112, CABA",
    "To": "Av. Santa Fe 113, CABA",
    "Description": "Servicio de transporte para Hogar Dulce Hogar",
    "ScheduledDate": "2025-03-20T00:00:00"
  },
  {
    "CustomerName": "Estilo Urbano",
    "From": "Calle Perú 334, CABA",
    "To": "Calle de la República 124, CABA",
    "Description": "Servicio de transporte para Estilo Urbano",
    "ScheduledDate": "2025-03-21T00:00:00"
  },
  {
    "CustomerName": "Viva Moda",
    "From": "Av. Belgrano 556, CABA",
    "To": "Av. de Mayo 235, CABA",
    "Description": "Servicio de transporte para Viva Moda",
    "ScheduledDate": "2025-02-21T00:00:00"
  },
  {
    "CustomerName": "Boutique Capital",
    "From": "Calle Sarmiento 778, CABA",
    "To": "Calle Esmeralda 346, CABA",
    "Description": "Servicio de transporte para Boutique Capital",
    "ScheduledDate": "2025-02-24T00:00:00"
  },
  {
    "CustomerName": "Gourmet Selecto",
    "From": "Av. Independencia 990, CABA",
    "To": "Av. Libertador 457, CABA",
    "Description": "Servicio de transporte para Gourmet Selecto",
    "ScheduledDate": "2025-02-25T00:00:00"
  },
  {
    "CustomerName": "Delicias del Mercado",
    "From": "Calle Bolívar 221, CABA",
    "To": "Calle Belgrano 568, CABA",
    "Description": "Servicio de transporte para Delicias del Mercado",
    "ScheduledDate": "2025-02-26T00:00:00"
  },
  {
    "CustomerName": "Sabores y Colores",
    "From": "Av. Entre Ríos 443, CABA",
    "To": "Av. del Libertador 679, CABA",
    "Description": "Servicio de transporte para Sabores y Colores",
    "ScheduledDate": "2025-02-27T00:00:00"
  },
  {
    "CustomerName": "Frescura Urbana",
    "From": "Av. Lavalle 665, CABA",
    "To": "Calle Alsina 780, CABA",
    "Description": "Servicio de transporte para Frescura Urbana",
    "ScheduledDate": "2025-02-28T00:00:00"
  },
  {
    "CustomerName": "Mosaico Cultural",
    "From": "Calle Moreno 887, CABA",
    "To": "Av. Congreso 891, CABA",
    "Description": "Servicio de transporte para Mosaico Cultural",
    "ScheduledDate": "2025-03-03T00:00:00"
  },
  {
    "CustomerName": "Arte y Pasión",
    "From": "Av. Maipú 109, CABA",
    "To": "Calle San Juan 902, CABA",
    "Description": "Servicio de transporte para Arte y Pasión",
    "ScheduledDate": "2025-03-04T00:00:00"
  },
  {
    "CustomerName": "Ritmo y Sabor",
    "From": "Calle Tucumán 312, CABA",
    "To": "Av. Maipú 103, CABA",
    "Description": "Servicio de transporte para Ritmo y Sabor",
    "ScheduledDate": "2025-03-05T00:00:00"
  },
  {
    "CustomerName": "Voz del Pueblo",
    "From": "Av. Congreso 534, CABA",
    "To": "Calle San Lorenzo 214, CABA",
    "Description": "Servicio de transporte para Voz del Pueblo",
    "ScheduledDate": "2025-03-06T00:00:00"
  },
  {
    "CustomerName": "Cultura y Tradición",
    "From": "Calle Alsina 756, CABA",
    "To": "Av. General Paz 325, CABA",
    "Description": "Servicio de transporte para Cultura y Tradición",
    "ScheduledDate": "2025-03-07T00:00:00"
  },
  {
    "CustomerName": "Expresión Moderna",
    "From": "Av. de los Incas 978, CABA",
    "To": "Calle Dorrego 436, CABA",
    "Description": "Servicio de transporte para Expresión Moderna",
    "ScheduledDate": "2025-03-10T00:00:00"
  },
  {
    "CustomerName": "Identidad Urbana",
    "From": "Calle San Juan 190, CABA",
    "To": "Av. Lavalle 547, CABA",
    "Description": "Servicio de transporte para Identidad Urbana",
    "ScheduledDate": "2025-03-11T00:00:00"
  },
  {
    "CustomerName": "Fusión Cultural",
    "From": "Av. Roca 212, CABA",
    "To": "Calle Mitre 658, CABA",
    "Description": "Servicio de transporte para Fusión Cultural",
    "ScheduledDate": "2025-03-12T00:00:00"
  },
  {
    "CustomerName": "Visión Integral",
    "From": "Calle 25 de Mayo 234, CABA",
    "To": "Av. Córdoba 769, CABA",
    "Description": "Servicio de transporte para Visión Integral",
    "ScheduledDate": "2025-03-13T00:00:00"
  },
  {
    "CustomerName": "Estrategia Global",
    "From": "Av. Juan B. Justo 456, CABA",
    "To": "Calle Independencia 880, CABA",
    "Description": "Servicio de transporte para Estrategia Global",
    "ScheduledDate": "2025-03-14T00:00:00"
  },
  {
    "CustomerName": "Mente Abierta",
    "From": "Calle Esmeralda 678, CABA",
    "To": "Av. Entre Ríos 991, CABA",
    "Description": "Servicio de transporte para Mente Abierta",
    "ScheduledDate": "2025-03-17T00:00:00"
  },
  {
    "CustomerName": "Conexión Directa",
    "From": "Av. General Paz 890, CABA",
    "To": "Calle Sarmiento 102, CABA",
    "Description": "Servicio de transporte para Conexión Directa",
    "ScheduledDate": "2025-03-18T00:00:00"
  },
  {
    "CustomerName": "Impulso Vital",
    "From": "Calle San Lorenzo 101, CABA",
    "To": "Av. 25 de Mayo 213, CABA",
    "Description": "Servicio de transporte para Impulso Vital",
    "ScheduledDate": "2025-03-19T00:00:00"
  },
  {
    "CustomerName": "Energía Positiva",
    "From": "Av. Paseo Colón 202, CABA",
    "To": "Calle Roque Sáenz Peña 324, CABA",
    "Description": "Servicio de transporte para Energía Positiva",
    "ScheduledDate": "2025-03-20T00:00:00"
  },
  {
    "CustomerName": "Rumbo Claro",
    "From": "Calle Dorrego 303, CABA",
    "To": "Av. Juan B. Justo 435, CABA",
    "Description": "Servicio de transporte para Rumbo Claro",
    "ScheduledDate": "2025-03-21T00:00:00"
  },
  {
    "CustomerName": "Meta Innovadora",
    "From": "Av. Córdoba 404, CABA",
    "To": "Calle Corrientes 546, CABA",
    "Description": "Servicio de transporte para Meta Innovadora",
    "ScheduledDate": "2025-02-21T00:00:00"
  },
  {
    "CustomerName": "Progreso Unido",
    "From": "Calle Mitre 505, CABA",
    "To": "Av. Santa Fe 657, CABA",
    "Description": "Servicio de transporte para Progreso Unido",
    "ScheduledDate": "2025-02-24T00:00:00"
  },
  {
    "CustomerName": "Futuro Brillante",
    "From": "Av. Belgrano 606, CABA",
    "To": "Calle Callao 768, CABA",
    "Description": "Servicio de transporte para Futuro Brillante",
    "ScheduledDate": "2025-02-25T00:00:00"
  },    
  {
      "CustomerName": "Innovar S.A.",
      "From": "Av. Corrientes 1234, CABA",
      "To": "Av. San Martín 1300, CABA",
      "Description": "Servicio de transporte para Innovar S.A.",
      "ScheduledDate": "2025-03-21T00:00:00"
    },
    {
      "CustomerName": "Alimentos del Sol",
      "From": "Av. Santa Fe 567, CABA",
      "To": "Calle Juramento 142, CABA",
      "Description": "Servicio de transporte para Alimentos del Sol",
      "ScheduledDate": "2025-03-24T00:00:00"
    },
    {
      "CustomerName": "Constructora Aurora",
      "From": "Av. Callao 890, CABA",
      "To": "Av. Corrientes 2500, CABA",
      "Description": "Servicio de transporte para Constructora Aurora",
      "ScheduledDate": "2025-03-25T00:00:00"
    },
    {
      "CustomerName": "Inversiones Delta",
      "From": "Av. Rivadavia 2345, CABA",
      "To": "Calle Bolívar 360, CABA",
      "Description": "Servicio de transporte para Inversiones Delta",
      "ScheduledDate": "2025-03-26T00:00:00"
    },
    {
      "CustomerName": "Tecnologías Andes",
      "From": "Av. 9 de Julio 101, CABA",
      "To": "Av. Callao 470, CABA",
      "Description": "Servicio de transporte para Tecnologías Andes",
      "ScheduledDate": "2025-03-27T00:00:00"
    },
    {
      "CustomerName": "Consultora Montaña",
      "From": "Av. Pueyrredón 456, CABA",
      "To": "Calle Florida 580, CABA",
      "Description": "Servicio de transporte para Consultora Montaña",
      "ScheduledDate": "2025-03-28T00:00:00"
    },
    {
      "CustomerName": "Financiera Capital",
      "From": "Calle Florida 789, CABA",
      "To": "Av. Rivadavia 690, CABA",
      "Description": "Servicio de transporte para Financiera Capital",
      "ScheduledDate": "2025-03-31T00:00:00"
    },
    {
      "CustomerName": "Sistemas Urbanos",
      "From": "Av. del Libertador 321, CABA",
      "To": "Calle 9 de Julio 800, CABA",
      "Description": "Servicio de transporte para Sistemas Urbanos",
      "ScheduledDate": "2025-04-01T00:00:00"
    },
    {
      "CustomerName": "Seguros del Plata",
      "From": "Av. de Mayo 654, CABA",
      "To": "Av. Pueyrredón 910, CABA",
      "Description": "Servicio de transporte para Seguros del Plata",
      "ScheduledDate": "2025-04-02T00:00:00"
    },
    {
      "CustomerName": "Edificaciones Modernas",
      "From": "Av. Cerviño 987, CABA",
      "To": "Calle Tucumán 102, CABA",
      "Description": "Servicio de transporte para Edificaciones Modernas",
      "ScheduledDate": "2025-04-03T00:00:00"
    },
    {
      "CustomerName": "Vivero Tropical",
      "From": "Av. San Martín 112, CABA",
      "To": "Av. Santa Fe 113, CABA",
      "Description": "Servicio de transporte para Vivero Tropical",
      "ScheduledDate": "2025-04-04T00:00:00"
    },
    {
      "CustomerName": "Productos Naturales",
      "From": "Calle Perú 334, CABA",
      "To": "Calle de la República 124, CABA",
      "Description": "Servicio de transporte para Productos Naturales",
      "ScheduledDate": "2025-04-07T00:00:00"
    },
    {
      "CustomerName": "Grupo Sideral",
      "From": "Av. Belgrano 556, CABA",
      "To": "Av. de Mayo 235, CABA",
      "Description": "Servicio de transporte para Grupo Sideral",
      "ScheduledDate": "2025-04-08T00:00:00"
    },
    {
      "CustomerName": "Optima Salud",
      "From": "Calle Sarmiento 778, CABA",
      "To": "Calle Esmeralda 346, CABA",
      "Description": "Servicio de transporte para Optima Salud",
      "ScheduledDate": "2025-04-09T00:00:00"
    },
    {
      "CustomerName": "Energía Renovable",
      "From": "Av. Independencia 990, CABA",
      "To": "Av. Libertador 457, CABA",
      "Description": "Servicio de transporte para Energía Renovable",
      "ScheduledDate": "2025-04-10T00:00:00"
    },
    {
      "CustomerName": "Futuro Digital",
      "From": "Calle Bolívar 221, CABA",
      "To": "Calle Belgrano 568, CABA",
      "Description": "Servicio de transporte para Futuro Digital",
      "ScheduledDate": "2025-04-11T00:00:00"
    },
    {
      "CustomerName": "Mundo Verde",
      "From": "Av. Entre Ríos 443, CABA",
      "To": "Av. del Libertador 679, CABA",
      "Description": "Servicio de transporte para Mundo Verde",
      "ScheduledDate": "2025-04-14T00:00:00"
    },
    {
      "CustomerName": "Artesanía Criolla",
      "From": "Av. Lavalle 665, CABA",
      "To": "Calle Alsina 780, CABA",
      "Description": "Servicio de transporte para Artesanía Criolla",
      "ScheduledDate": "2025-04-15T00:00:00"
    },
    {
      "CustomerName": "Estilo y Diseño",
      "From": "Calle Moreno 887, CABA",
      "To": "Av. Congreso 891, CABA",
      "Description": "Servicio de transporte para Estilo y Diseño",
      "ScheduledDate": "2025-04-16T00:00:00"
    },
    {
      "CustomerName": "Cultura Viva",
      "From": "Av. Maipú 109, CABA",
      "To": "Calle San Juan 902, CABA",
      "Description": "Servicio de transporte para Cultura Viva",
      "ScheduledDate": "2025-04-17T00:00:00"
    },
    {
      "CustomerName": "Vanguardia Empresarial",
      "From": "Calle Tucumán 312, CABA",
      "To": "Av. Maipú 103, CABA",
      "Description": "Servicio de transporte para Vanguardia Empresarial",
      "ScheduledDate": "2025-04-18T00:00:00"
    },
    {
      "CustomerName": "Nexo Innovación",
      "From": "Av. Congreso 534, CABA",
      "To": "Calle San Lorenzo 214, CABA",
      "Description": "Servicio de transporte para Nexo Innovación",
      "ScheduledDate": "2025-03-21T00:00:00"
    },
    {
      "CustomerName": "Soluciones Integrales",
      "From": "Calle Alsina 756, CABA",
      "To": "Av. General Paz 325, CABA",
      "Description": "Servicio de transporte para Soluciones Integrales",
      "ScheduledDate": "2025-03-24T00:00:00"
    },
    {
      "CustomerName": "Horizonte Financiero",
      "From": "Av. de los Incas 978, CABA",
      "To": "Calle Dorrego 436, CABA",
      "Description": "Servicio de transporte para Horizonte Financiero",
      "ScheduledDate": "2025-03-25T00:00:00"
    },
    {
      "CustomerName": "Impulso Creativo",
      "From": "Calle San Juan 190, CABA",
      "To": "Av. Lavalle 547, CABA",
      "Description": "Servicio de transporte para Impulso Creativo",
      "ScheduledDate": "2025-03-26T00:00:00"
    },
    {
      "CustomerName": "Red Empresarial",
      "From": "Av. Roca 212, CABA",
      "To": "Calle Mitre 658, CABA",
      "Description": "Servicio de transporte para Red Empresarial",
      "ScheduledDate": "2025-03-27T00:00:00"
    },
    {
      "CustomerName": "Natura Organics",
      "From": "Calle 25 de Mayo 234, CABA",
      "To": "Av. Córdoba 769, CABA",
      "Description": "Servicio de transporte para Natura Organics",
      "ScheduledDate": "2025-03-28T00:00:00"
    },
    {
      "CustomerName": "Calidad Premium",
      "From": "Av. Juan B. Justo 456, CABA",
      "To": "Calle Independencia 880, CABA",
      "Description": "Servicio de transporte para Calidad Premium",
      "ScheduledDate": "2025-03-31T00:00:00"
    },
    {
      "CustomerName": "EcoVida",
      "From": "Calle Esmeralda 678, CABA",
      "To": "Av. Entre Ríos 991, CABA",
      "Description": "Servicio de transporte para EcoVida",
      "ScheduledDate": "2025-04-01T00:00:00"
    },
    {
      "CustomerName": "Gourmet Delicias",
      "From": "Av. General Paz 890, CABA",
      "To": "Calle Sarmiento 102, CABA",
      "Description": "Servicio de transporte para Gourmet Delicias",
      "ScheduledDate": "2025-04-02T00:00:00"
    },
    {
      "CustomerName": "Sabor y Tradición",
      "From": "Calle San Lorenzo 101, CABA",
      "To": "Av. 25 de Mayo 213, CABA",
      "Description": "Servicio de transporte para Sabor y Tradición",
      "ScheduledDate": "2025-04-03T00:00:00"
    },
    {
      "CustomerName": "Cine & Arte",
      "From": "Av. Paseo Colón 202, CABA",
      "To": "Calle Roque Sáenz Peña 324, CABA",
      "Description": "Servicio de transporte para Cine & Arte",
      "ScheduledDate": "2025-04-04T00:00:00"
    },
    {
      "CustomerName": "Música Latina",
      "From": "Calle Dorrego 303, CABA",
      "To": "Av. Juan B. Justo 435, CABA",
      "Description": "Servicio de transporte para Música Latina",
      "ScheduledDate": "2025-04-07T00:00:00"
    },
    {
      "CustomerName": "Estudios Arco",
      "From": "Av. Córdoba 404, CABA",
      "To": "Calle Corrientes 546, CABA",
      "Description": "Servicio de transporte para Estudios Arco",
      "ScheduledDate": "2025-04-08T00:00:00"
    },
    {
      "CustomerName": "MediaFusión",
      "From": "Calle Mitre 505, CABA",
      "To": "Av. Santa Fe 657, CABA",
      "Description": "Servicio de transporte para MediaFusión",
      "ScheduledDate": "2025-04-09T00:00:00"
    },
    {
      "CustomerName": "Tecnova",
      "From": "Av. Belgrano 606, CABA",
      "To": "Calle Callao 768, CABA",
      "Description": "Servicio de transporte para Tecnova",
      "ScheduledDate": "2025-04-10T00:00:00"
    },
    {
      "CustomerName": "Pixel Creativo",
      "From": "Calle Lavalle 707, CABA",
      "To": "Av. Roca 879, CABA",
      "Description": "Servicio de transporte para Pixel Creativo",
      "ScheduledDate": "2025-04-11T00:00:00"
    },
    {
      "CustomerName": "Digital Minds",
      "From": "Av. Roque Sáenz Peña 808, CABA",
      "To": "Calle Belgrano 980, CABA",
      "Description": "Servicio de transporte para Digital Minds",
      "ScheduledDate": "2025-04-14T00:00:00"
    },
    {
      "CustomerName": "DataWave",
      "From": "Av. Corrientes 1234, CABA",
      "To": "Av. San Martín 1300, CABA",
      "Description": "Servicio de transporte para DataWave",
      "ScheduledDate": "2025-04-15T00:00:00"
    },
    {
      "CustomerName": "InfoTech Solutions",
      "From": "Av. Santa Fe 567, CABA",
      "To": "Calle Juramento 142, CABA",
      "Description": "Servicio de transporte para InfoTech Solutions",
      "ScheduledDate": "2025-04-16T00:00:00"
    },
    {
      "CustomerName": "Innovación Global",
      "From": "Av. Callao 890, CABA",
      "To": "Av. Corrientes 2500, CABA",
      "Description": "Servicio de transporte para Innovación Global",
      "ScheduledDate": "2025-04-17T00:00:00"
    },
    {
      "CustomerName": "Smart Business",
      "From": "Av. Rivadavia 2345, CABA",
      "To": "Calle Bolívar 360, CABA",
      "Description": "Servicio de transporte para Smart Business",
      "ScheduledDate": "2025-04-18T00:00:00"
    },
    {
      "CustomerName": "Alpha Invest",
      "From": "Av. 9 de Julio 101, CABA",
      "To": "Av. Callao 470, CABA",
      "Description": "Servicio de transporte para Alpha Invest",
      "ScheduledDate": "2025-03-21T00:00:00"
    },
    {
      "CustomerName": "Beta Corp",
      "From": "Av. Pueyrredón 456, CABA",
      "To": "Calle Florida 580, CABA",
      "Description": "Servicio de transporte para Beta Corp",
      "ScheduledDate": "2025-03-24T00:00:00"
    },
    {
      "CustomerName": "Gamma Holdings",
      "From": "Calle Florida 789, CABA",
      "To": "Av. Rivadavia 690, CABA",
      "Description": "Servicio de transporte para Gamma Holdings",
      "ScheduledDate": "2025-03-25T00:00:00"
    },
    {
      "CustomerName": "Omega Industries",
      "From": "Av. del Libertador 321, CABA",
      "To": "Calle 9 de Julio 800, CABA",
      "Description": "Servicio de transporte para Omega Industries",
      "ScheduledDate": "2025-03-26T00:00:00"
    },
    {
      "CustomerName": "Sigma Enterprises",
      "From": "Av. de Mayo 654, CABA",
      "To": "Av. Pueyrredón 910, CABA",
      "Description": "Servicio de transporte para Sigma Enterprises",
      "ScheduledDate": "2025-03-27T00:00:00"
    },
    {
      "CustomerName": "Delta Services",
      "From": "Av. Cerviño 987, CABA",
      "To": "Calle Tucumán 102, CABA",
      "Description": "Servicio de transporte para Delta Services",
      "ScheduledDate": "2025-03-28T00:00:00"
    },
    {
      "CustomerName": "Epsilon Group",
      "From": "Av. San Martín 112, CABA",
      "To": "Av. Santa Fe 113, CABA",
      "Description": "Servicio de transporte para Epsilon Group",
      "ScheduledDate": "2025-03-31T00:00:00"
    },
    {
      "CustomerName": "Zeta Solutions",
      "From": "Calle Perú 334, CABA",
      "To": "Calle de la República 124, CABA",
      "Description": "Servicio de transporte para Zeta Solutions",
      "ScheduledDate": "2025-04-01T00:00:00"
    },
    {
      "CustomerName": "Kappa Consulting",
      "From": "Av. Belgrano 556, CABA",
      "To": "Av. de Mayo 235, CABA",
      "Description": "Servicio de transporte para Kappa Consulting",
      "ScheduledDate": "2025-04-02T00:00:00"
    },
    {
      "CustomerName": "Lambda Ventures",
      "From": "Calle Sarmiento 778, CABA",
      "To": "Calle Esmeralda 346, CABA",
      "Description": "Servicio de transporte para Lambda Ventures",
      "ScheduledDate": "2025-04-03T00:00:00"
    },
    {
      "CustomerName": "Nu Capital",
      "From": "Av. Independencia 990, CABA",
      "To": "Av. Libertador 457, CABA",
      "Description": "Servicio de transporte para Nu Capital",
      "ScheduledDate": "2025-04-04T00:00:00"
    },
    {
      "CustomerName": "Omicron Technologies",
      "From": "Calle Bolívar 221, CABA",
      "To": "Calle Belgrano 568, CABA",
      "Description": "Servicio de transporte para Omicron Technologies",
      "ScheduledDate": "2025-04-07T00:00:00"
    },
    {
      "CustomerName": "Pi Electronics",
      "From": "Av. Entre Ríos 443, CABA",
      "To": "Av. del Libertador 679, CABA",
      "Description": "Servicio de transporte para Pi Electronics",
      "ScheduledDate": "2025-04-08T00:00:00"
    },
    {
      "CustomerName": "Rho Retail",
      "From": "Av. Lavalle 665, CABA",
      "To": "Calle Alsina 780, CABA",
      "Description": "Servicio de transporte para Rho Retail",
      "ScheduledDate": "2025-04-09T00:00:00"
    },
    {
      "CustomerName": "Tau Foods",
      "From": "Calle Moreno 887, CABA",
      "To": "Av. Congreso 891, CABA",
      "Description": "Servicio de transporte para Tau Foods",
      "ScheduledDate": "2025-04-10T00:00:00"
    },
    {
      "CustomerName": "Upsilon Pharma",
      "From": "Av. Maipú 109, CABA",
      "To": "Calle San Juan 902, CABA",
      "Description": "Servicio de transporte para Upsilon Pharma",
      "ScheduledDate": "2025-04-11T00:00:00"
    },
    {
      "CustomerName": "Phi Beverages",
      "From": "Calle Tucumán 312, CABA",
      "To": "Av. Maipú 103, CABA",
      "Description": "Servicio de transporte para Phi Beverages",
      "ScheduledDate": "2025-04-14T00:00:00"
    },
    {
      "CustomerName": "Chi Textiles",
      "From": "Av. Congreso 534, CABA",
      "To": "Calle San Lorenzo 214, CABA",
      "Description": "Servicio de transporte para Chi Textiles",
      "ScheduledDate": "2025-04-15T00:00:00"
    },
    {
      "CustomerName": "Psi Chemicals",
      "From": "Calle Alsina 756, CABA",
      "To": "Av. General Paz 325, CABA",
      "Description": "Servicio de transporte para Psi Chemicals",
      "ScheduledDate": "2025-04-16T00:00:00"
    },
    {
      "CustomerName": "Omega Materials",
      "From": "Av. de los Incas 978, CABA",
      "To": "Calle Dorrego 436, CABA",
      "Description": "Servicio de transporte para Omega Materials",
      "ScheduledDate": "2025-04-17T00:00:00"
    },
    {
      "CustomerName": "Nueva Imagen",
      "From": "Calle San Juan 190, CABA",
      "To": "Av. Lavalle 547, CABA",
      "Description": "Servicio de transporte para Nueva Imagen",
      "ScheduledDate": "2025-04-18T00:00:00"
    },
    {
      "CustomerName": "Brillante Ideas",
      "From": "Av. Roca 212, CABA",
      "To": "Calle Mitre 658, CABA",
      "Description": "Servicio de transporte para Brillante Ideas",
      "ScheduledDate": "2025-03-21T00:00:00"
    },
    {
      "CustomerName": "Cumbre Creativa",
      "From": "Calle 25 de Mayo 234, CABA",
      "To": "Av. Córdoba 769, CABA",
      "Description": "Servicio de transporte para Cumbre Creativa",
      "ScheduledDate": "2025-03-24T00:00:00"
    },
    {
      "CustomerName": "Faro Empresarial",
      "From": "Av. Juan B. Justo 456, CABA",
      "To": "Calle Independencia 880, CABA",
      "Description": "Servicio de transporte para Faro Empresarial",
      "ScheduledDate": "2025-03-25T00:00:00"
    },
    {
      "CustomerName": "Punto de Encuentro",
      "From": "Calle Esmeralda 678, CABA",
      "To": "Av. Entre Ríos 991, CABA",
      "Description": "Servicio de transporte para Punto de Encuentro",
      "ScheduledDate": "2025-03-26T00:00:00"
    },
    {
      "CustomerName": "Clave Urbana",
      "From": "Av. General Paz 890, CABA",
      "To": "Calle Sarmiento 102, CABA",
      "Description": "Servicio de transporte para Clave Urbana",
      "ScheduledDate": "2025-03-27T00:00:00"
    },
    {
      "CustomerName": "Estrella del Norte",
      "From": "Calle San Lorenzo 101, CABA",
      "To": "Av. 25 de Mayo 213, CABA",
      "Description": "Servicio de transporte para Estrella del Norte",
      "ScheduledDate": "2025-03-28T00:00:00"
    },
    {
      "CustomerName": "Aurora Global",
      "From": "Av. Paseo Colón 202, CABA",
      "To": "Calle Roque Sáenz Peña 324, CABA",
      "Description": "Servicio de transporte para Aurora Global",
      "ScheduledDate": "2025-03-31T00:00:00"
    },
    {
      "CustomerName": "Sol Naciente",
      "From": "Calle Dorrego 303, CABA",
      "To": "Av. Juan B. Justo 435, CABA",
      "Description": "Servicio de transporte para Sol Naciente",
      "ScheduledDate": "2025-04-01T00:00:00"
    },
    {
      "CustomerName": "Luz de Plata",
      "From": "Av. Córdoba 404, CABA",
      "To": "Calle Corrientes 546, CABA",
      "Description": "Servicio de transporte para Luz de Plata",
      "ScheduledDate": "2025-04-02T00:00:00"
    },
    {
      "CustomerName": "Manantial Natural",
      "From": "Calle Mitre 505, CABA",
      "To": "Av. Santa Fe 657, CABA",
      "Description": "Servicio de transporte para Manantial Natural",
      "ScheduledDate": "2025-04-03T00:00:00"
    },
    {
      "CustomerName": "Fuente de Vida",
      "From": "Av. Belgrano 606, CABA",
      "To": "Calle Callao 768, CABA",
      "Description": "Servicio de transporte para Fuente de Vida",
      "ScheduledDate": "2025-04-04T00:00:00"
    },
    {
      "CustomerName": "Corazón Argentino",
      "From": "Calle Lavalle 707, CABA",
      "To": "Av. Roca 879, CABA",
      "Description": "Servicio de transporte para Corazón Argentino",
      "ScheduledDate": "2025-04-07T00:00:00"
    },
    {
      "CustomerName": "Patrimonio Vivo",
      "From": "Av. Roque Sáenz Peña 808, CABA",
      "To": "Calle Belgrano 980, CABA",
      "Description": "Servicio de transporte para Patrimonio Vivo",
      "ScheduledDate": "2025-04-08T00:00:00"
    },
    {
      "CustomerName": "Raíces y Alas",
      "From": "Av. Corrientes 1234, CABA",
      "To": "Av. San Martín 1300, CABA",
      "Description": "Servicio de transporte para Raíces y Alas",
      "ScheduledDate": "2025-04-09T00:00:00"
    },
    {
      "CustomerName": "Sueño Dorado",
      "From": "Av. Santa Fe 567, CABA",
      "To": "Calle Juramento 142, CABA",
      "Description": "Servicio de transporte para Sueño Dorado",
      "ScheduledDate": "2025-04-10T00:00:00"
    },
    {
      "CustomerName": "Horizonte Claro",
      "From": "Av. Callao 890, CABA",
      "To": "Av. Corrientes 2500, CABA",
      "Description": "Servicio de transporte para Horizonte Claro",
      "ScheduledDate": "2025-04-11T00:00:00"
    },
    {
      "CustomerName": "Visión Serena",
      "From": "Av. Rivadavia 2345, CABA",
      "To": "Calle Bolívar 360, CABA",
      "Description": "Servicio de transporte para Visión Serena",
      "ScheduledDate": "2025-04-14T00:00:00"
    },
    {
      "CustomerName": "Imaginarium",
      "From": "Av. 9 de Julio 101, CABA",
      "To": "Calle Juramento 142, CABA",
      "Description": "Servicio de transporte para Imaginarium",
      "ScheduledDate": "2025-04-15T00:00:00"
    },
    {
      "CustomerName": "Ideas Frescas",
      "From": "Av. Pueyrredón 456, CABA",
      "To": "Calle Florida 580, CABA",
      "Description": "Servicio de transporte para Ideas Frescas",
      "ScheduledDate": "2025-04-16T00:00:00"
    },
    {
      "CustomerName": "Espacio Innovador",
      "From": "Calle Florida 789, CABA",
      "To": "Av. Rivadavia 690, CABA",
      "Description": "Servicio de transporte para Espacio Innovador",
      "ScheduledDate": "2025-04-17T00:00:00"
    },
    {
      "CustomerName": "Planeta Verde",
      "From": "Av. del Libertador 321, CABA",
      "To": "Calle 9 de Julio 800, CABA",
      "Description": "Servicio de transporte para Planeta Verde",
      "ScheduledDate": "2025-04-18T00:00:00"
    },
    {
      "CustomerName": "Marea Alta",
      "From": "Av. de Mayo 654, CABA",
      "To": "Av. Pueyrredón 910, CABA",
      "Description": "Servicio de transporte para Marea Alta",
      "ScheduledDate": "2025-03-21T00:00:00"
    },
    {
      "CustomerName": "Río Claro",
      "From": "Av. Cerviño 987, CABA",
      "To": "Calle Tucumán 102, CABA",
      "Description": "Servicio de transporte para Río Claro",
      "ScheduledDate": "2025-03-24T00:00:00"
    },
    {
      "CustomerName": "Lago Azul",
      "From": "Av. San Martín 112, CABA",
      "To": "Av. Santa Fe 113, CABA",
      "Description": "Servicio de transporte para Lago Azul",
      "ScheduledDate": "2025-03-25T00:00:00"
    },
    {
      "CustomerName": "Valle Encantado",
      "From": "Calle Perú 334, CABA",
      "To": "Calle de la República 124, CABA",
      "Description": "Servicio de transporte para Valle Encantado",
      "ScheduledDate": "2025-03-26T00:00:00"
    },
    {
      "CustomerName": "Cumbre Andina",
      "From": "Av. Belgrano 556, CABA",
      "To": "Av. de Mayo 235, CABA",
      "Description": "Servicio de transporte para Cumbre Andina",
      "ScheduledDate": "2025-03-27T00:00:00"
    },
    {
      "CustomerName": "Pampa Serena",
      "From": "Calle Sarmiento 778, CABA",
      "To": "Calle Esmeralda 346, CABA",
      "Description": "Servicio de transporte para Pampa Serena",
      "ScheduledDate": "2025-03-28T00:00:00"
    },
    {
      "CustomerName": "Sol y Sombra",
      "From": "Av. Independencia 990, CABA",
      "To": "Av. Libertador 457, CABA",
      "Description": "Servicio de transporte para Sol y Sombra",
      "ScheduledDate": "2025-03-31T00:00:00"
    },
    {
      "CustomerName": "Luz y Vida",
      "From": "Calle Bolívar 221, CABA",
      "To": "Calle Belgrano 568, CABA",
      "Description": "Servicio de transporte para Luz y Vida",
      "ScheduledDate": "2025-04-01T00:00:00"
    },
    {
      "CustomerName": "Amanecer Dorado",
      "From": "Calle Mitre 505, CABA",
      "To": "Av. Santa Fe 657, CABA",
      "Description": "Servicio de transporte para Amanecer Dorado",
      "ScheduledDate": "2025-04-02T00:00:00"
    },
    {
      "CustomerName": "Reflejo Urbano",
      "From": "Av. Belgrano 606, CABA",
      "To": "Calle Callao 768, CABA",
      "Description": "Servicio de transporte para Reflejo Urbano",
      "ScheduledDate": "2025-04-03T00:00:00"
    },
    {
      "CustomerName": "Punto Focal",
      "From": "Calle Lavalle 707, CABA",
      "To": "Av. Roca 879, CABA",
      "Description": "Servicio de transporte para Punto Focal",
      "ScheduledDate": "2025-04-04T00:00:00"
    },
    {
      "CustomerName": "Núcleo Creativo",
      "From": "Av. Roque Sáenz Peña 808, CABA",
      "To": "Calle Belgrano 980, CABA",
      "Description": "Servicio de transporte para Núcleo Creativo",
      "ScheduledDate": "2025-04-07T00:00:00"
    },
    {
      "CustomerName": "Mente Brillante",
      "From": "Av. Corrientes 1234, CABA",
      "To": "Av. San Martín 1300, CABA",
      "Description": "Servicio de transporte para Mente Brillante",
      "ScheduledDate": "2025-04-08T00:00:00"
    },
    {
      "CustomerName": "Esencia Pura",
      "From": "Av. Santa Fe 567, CABA",
      "To": "Calle Juramento 142, CABA",
      "Description": "Servicio de transporte para Esencia Pura",
      "ScheduledDate": "2025-04-09T00:00:00"
    },
    {
      "CustomerName": "Sabor Natural",
      "From": "Av. Callao 890, CABA",
      "To": "Av. Corrientes 2500, CABA",
      "Description": "Servicio de transporte para Sabor Natural",
      "ScheduledDate": "2025-04-10T00:00:00"
    },
    {
      "CustomerName": "Delicias del Campo",
      "From": "Av. Rivadavia 2345, CABA",
      "To": "Calle Bolívar 360, CABA",
      "Description": "Servicio de transporte para Delicias del Campo",
      "ScheduledDate": "2025-04-11T00:00:00"
    },
    {
      "CustomerName": "Sabores del Valle",
      "From": "Av. 9 de Julio 101, CABA",
      "To": "Av. Callao 470, CABA",
      "Description": "Servicio de transporte para Sabores del Valle",
      "ScheduledDate": "2025-04-14T00:00:00"
    },
    {
      "CustomerName": "Frescura Extrema",
      "From": "Av. Pueyrredón 456, CABA",
      "To": "Calle Florida 580, CABA",
      "Description": "Servicio de transporte para Frescura Extrema",
      "ScheduledDate": "2025-04-15T00:00:00"
    },
    {
      "CustomerName": "Cosecha Dorada",
      "From": "Calle Florida 789, CABA",
      "To": "Av. Rivadavia 690, CABA",
      "Description": "Servicio de transporte para Cosecha Dorada",
      "ScheduledDate": "2025-04-16T00:00:00"
    },
    {
      "CustomerName": "Verde Vivo",
      "From": "Av. del Libertador 321, CABA",
      "To": "Calle 9 de Julio 800, CABA",
      "Description": "Servicio de transporte para Verde Vivo",
      "ScheduledDate": "2025-04-17T00:00:00"
    },
    {
      "CustomerName": "AgroPlus",
      "From": "Av. de Mayo 654, CABA",
      "To": "Av. Pueyrredón 910, CABA",
      "Description": "Servicio de transporte para AgroPlus",
      "ScheduledDate": "2025-04-18T00:00:00"
    },
    {
      "CustomerName": "Frutos del Sur",
      "From": "Calle San Lorenzo 101, CABA",
      "To": "Calle de la República 124, CABA",
      "Description": "Servicio de transporte para Frutos del Sur",
      "ScheduledDate": "2025-03-21T00:00:00"
    },
    {
      "CustomerName": "Natura Organix",
      "From": "Av. Paseo Colón 202, CABA",
      "To": "Calle Roque Sáenz Peña 324, CABA",
      "Description": "Servicio de transporte para Natura Organix",
      "ScheduledDate": "2025-03-24T00:00:00"
    },
    {
      "CustomerName": "Cultiva Bien",
      "From": "Calle Dorrego 303, CABA",
      "To": "Av. Juan B. Justo 435, CABA",
      "Description": "Servicio de transporte para Cultiva Bien",
      "ScheduledDate": "2025-03-25T00:00:00"
    },
    {
      "CustomerName": "Finca Real",
      "From": "Av. Córdoba 404, CABA",
      "To": "Calle Corrientes 546, CABA",
      "Description": "Servicio de transporte para Finca Real",
      "ScheduledDate": "2025-03-26T00:00:00"
    },
    {
      "CustomerName": "Granja del Sol",
      "From": "Calle Mitre 505, CABA",
      "To": "Av. Santa Fe 657, CABA",
      "Description": "Servicio de transporte para Granja del Sol",
      "ScheduledDate": "2025-03-27T00:00:00"
    },
    {
      "CustomerName": "Cosecha Selecta",
      "From": "Av. Belgrano 606, CABA",
      "To": "Calle Callao 768, CABA",
      "Description": "Servicio de transporte para Cosecha Selecta",
      "ScheduledDate": "2025-03-28T00:00:00"
    },
    {
      "CustomerName": "Campo Unido",
      "From": "Calle Lavalle 707, CABA",
      "To": "Av. Roca 879, CABA",
      "Description": "Servicio de transporte para Campo Unido",
      "ScheduledDate": "2025-03-31T00:00:00"
    },
    {
      "CustomerName": "Frescura Natural",
      "From": "Av. Roque Sáenz Peña 808, CABA",
      "To": "Calle Belgrano 980, CABA",
      "Description": "Servicio de transporte para Frescura Natural",
      "ScheduledDate": "2025-04-01T00:00:00"
    },
    {
      "CustomerName": "Vitamina S.A.",
      "From": "Av. Corrientes 1234, CABA",
      "To": "Av. San Martín 1300, CABA",
      "Description": "Servicio de transporte para Vitamina S.A.",
      "ScheduledDate": "2025-04-02T00:00:00"
    },
    {
      "CustomerName": "Sabor y Vida",
      "From": "Av. Santa Fe 567, CABA",
      "To": "Calle Juramento 142, CABA",
      "Description": "Servicio de transporte para Sabor y Vida",
      "ScheduledDate": "2025-04-03T00:00:00"
    },
    {
      "CustomerName": "Fusión Creativa",
      "From": "Av. Pueyrredón 456, CABA",
      "To": "Calle Florida 580, CABA",
      "Description": "Servicio de transporte para Fusión Creativa",
      "ScheduledDate": "2025-04-04T00:00:00"
    },
    {
      "CustomerName": "Armonía Global",
      "From": "Calle Florida 789, CABA",
      "To": "Av. Rivadavia 690, CABA",
      "Description": "Servicio de transporte para Armonía Global",
      "ScheduledDate": "2025-04-07T00:00:00"
    },
    {
      "CustomerName": "Ritmo Urbano",
      "From": "Av. del Libertador 321, CABA",
      "To": "Calle 9 de Julio 800, CABA",
      "Description": "Servicio de transporte para Ritmo Urbano",
      "ScheduledDate": "2025-04-08T00:00:00"
    },
    {
      "CustomerName": "Expreso Digital",
      "From": "Av. de Mayo 654, CABA",
      "To": "Av. Pueyrredón 910, CABA",
      "Description": "Servicio de transporte para Expreso Digital",
      "ScheduledDate": "2025-04-09T00:00:00"
    },
    {
      "CustomerName": "Eco Inteligente",
      "From": "Av. Cerviño 987, CABA",
      "To": "Calle Tucumán 102, CABA",
      "Description": "Servicio de transporte para Eco Inteligente",
      "ScheduledDate": "2025-04-10T00:00:00"
    },
    {
      "CustomerName": "EcoSustentable",
      "From": "Av. San Martín 112, CABA",
      "To": "Av. Santa Fe 113, CABA",
      "Description": "Servicio de transporte para EcoSustentable",
      "ScheduledDate": "2025-04-11T00:00:00"
    },
    {
      "CustomerName": "Verde Futuro",
      "From": "Calle Perú 334, CABA",
      "To": "Calle de la República 124, CABA",
      "Description": "Servicio de transporte para Verde Futuro",
      "ScheduledDate": "2025-04-14T00:00:00"
    },
    {
      "CustomerName": "Innovar Plus",
      "From": "Av. Belgrano 556, CABA",
      "To": "Av. de Mayo 235, CABA",
      "Description": "Servicio de transporte para Innovar Plus",
      "ScheduledDate": "2025-04-15T00:00:00"
    },
    {
      "CustomerName": "Clima Perfecto",
      "From": "Calle Sarmiento 778, CABA",
      "To": "Calle Esmeralda 346, CABA",
      "Description": "Servicio de transporte para Clima Perfecto",
      "ScheduledDate": "2025-04-16T00:00:00"
    },
    {
      "CustomerName": "Hogar Dulce Hogar",
      "From": "Av. Independencia 990, CABA",
      "To": "Av. Libertador 457, CABA",
      "Description": "Servicio de transporte para Hogar Dulce Hogar",
      "ScheduledDate": "2025-04-17T00:00:00"
    },
    {
      "CustomerName": "Estilo Urbano",
      "From": "Calle Bolívar 221, CABA",
      "To": "Calle Belgrano 568, CABA",
      "Description": "Servicio de transporte para Estilo Urbano",
      "ScheduledDate": "2025-04-18T00:00:00"
    },
    {
      "CustomerName": "Innovar S.A.",
      "From": "Av. Corrientes 1234, CABA",
      "To": "Av. San Martín 1300, CABA",
      "Description": "Servicio de transporte para Innovar S.A.",
      "ScheduledDate": "2025-03-21T00:00:00"
    },
    {
      "CustomerName": "Alimentos del Sol",
      "From": "Av. Santa Fe 567, CABA",
      "To": "Calle Juramento 142, CABA",
      "Description": "Servicio de transporte para Alimentos del Sol",
      "ScheduledDate": "2025-03-24T00:00:00"
    },
    {
      "CustomerName": "Constructora Aurora",
      "From": "Av. Callao 890, CABA",
      "To": "Av. Corrientes 2500, CABA",
      "Description": "Servicio de transporte para Constructora Aurora",
      "ScheduledDate": "2025-03-25T00:00:00"
    },
    {
      "CustomerName": "Inversiones Delta",
      "From": "Av. Rivadavia 2345, CABA",
      "To": "Calle Bolívar 360, CABA",
      "Description": "Servicio de transporte para Inversiones Delta",
      "ScheduledDate": "2025-03-26T00:00:00"
    },
    {
      "CustomerName": "Tecnologías Andes",
      "From": "Av. 9 de Julio 101, CABA",
      "To": "Av. Callao 470, CABA",
      "Description": "Servicio de transporte para Tecnologías Andes",
      "ScheduledDate": "2025-03-27T00:00:00"
    },
    {
      "CustomerName": "Consultora Montaña",
      "From": "Av. Pueyrredón 456, CABA",
      "To": "Calle Florida 580, CABA",
      "Description": "Servicio de transporte para Consultora Montaña",
      "ScheduledDate": "2025-03-28T00:00:00"
    },
    {
      "CustomerName": "Financiera Capital",
      "From": "Calle Florida 789, CABA",
      "To": "Av. Rivadavia 690, CABA",
      "Description": "Servicio de transporte para Financiera Capital",
      "ScheduledDate": "2025-03-31T00:00:00"
    },
    {
      "CustomerName": "Sistemas Urbanos",
      "From": "Av. del Libertador 321, CABA",
      "To": "Calle 9 de Julio 800, CABA",
      "Description": "Servicio de transporte para Sistemas Urbanos",
      "ScheduledDate": "2025-04-01T00:00:00"
    },
    {
      "CustomerName": "Seguros del Plata",
      "From": "Av. de Mayo 654, CABA",
      "To": "Av. Pueyrredón 910, CABA",
      "Description": "Servicio de transporte para Seguros del Plata",
      "ScheduledDate": "2025-04-02T00:00:00"
    },
    {
      "CustomerName": "Edificaciones Modernas",
      "From": "Av. Cerviño 987, CABA",
      "To": "Calle Tucumán 102, CABA",
      "Description": "Servicio de transporte para Edificaciones Modernas",
      "ScheduledDate": "2025-04-03T00:00:00"
    },
    {
      "CustomerName": "Vivero Tropical",
      "From": "Av. San Martín 112, CABA",
      "To": "Av. Santa Fe 113, CABA",
      "Description": "Servicio de transporte para Vivero Tropical",
      "ScheduledDate": "2025-04-04T00:00:00"
    },
    {
      "CustomerName": "Productos Naturales",
      "From": "Calle Perú 334, CABA",
      "To": "Calle de la República 124, CABA",
      "Description": "Servicio de transporte para Productos Naturales",
      "ScheduledDate": "2025-04-07T00:00:00"
    },
    {
      "CustomerName": "Grupo Sideral",
      "From": "Av. Belgrano 556, CABA",
      "To": "Av. de Mayo 235, CABA",
      "Description": "Servicio de transporte para Grupo Sideral",
      "ScheduledDate": "2025-04-08T00:00:00"
    },
    {
      "CustomerName": "Optima Salud",
      "From": "Calle Sarmiento 778, CABA",
      "To": "Calle Esmeralda 346, CABA",
      "Description": "Servicio de transporte para Optima Salud",
      "ScheduledDate": "2025-04-09T00:00:00"
    },
    {
      "CustomerName": "Energía Renovable",
      "From": "Av. Independencia 990, CABA",
      "To": "Av. Libertador 457, CABA",
      "Description": "Servicio de transporte para Energía Renovable",
      "ScheduledDate": "2025-04-10T00:00:00"
    },
    {
      "CustomerName": "Futuro Digital",
      "From": "Calle Bolívar 221, CABA",
      "To": "Calle Belgrano 568, CABA",
      "Description": "Servicio de transporte para Futuro Digital",
      "ScheduledDate": "2025-04-11T00:00:00"
    },
    {
      "CustomerName": "Mundo Verde",
      "From": "Av. Entre Ríos 443, CABA",
      "To": "Av. del Libertador 679, CABA",
      "Description": "Servicio de transporte para Mundo Verde",
      "ScheduledDate": "2025-04-14T00:00:00"
    },
    {
      "CustomerName": "Artesanía Criolla",
      "From": "Av. Lavalle 665, CABA",
      "To": "Calle Alsina 780, CABA",
      "Description": "Servicio de transporte para Artesanía Criolla",
      "ScheduledDate": "2025-04-15T00:00:00"
    },
    {
      "CustomerName": "Estilo y Diseño",
      "From": "Calle Moreno 887, CABA",
      "To": "Av. Congreso 891, CABA",
      "Description": "Servicio de transporte para Estilo y Diseño",
      "ScheduledDate": "2025-04-16T00:00:00"
    },
    {
      "CustomerName": "Cultura Viva",
      "From": "Av. Maipú 109, CABA",
      "To": "Calle San Juan 902, CABA",
      "Description": "Servicio de transporte para Cultura Viva",
      "ScheduledDate": "2025-04-17T00:00:00"
    },
    {
      "CustomerName": "Vanguardia Empresarial",
      "From": "Calle Tucumán 312, CABA",
      "To": "Av. Maipú 103, CABA",
      "Description": "Servicio de transporte para Vanguardia Empresarial",
      "ScheduledDate": "2025-04-18T00:00:00"
    },
    {
      "CustomerName": "Nexo Innovación",
      "From": "Av. Congreso 534, CABA",
      "To": "Calle San Lorenzo 214, CABA",
      "Description": "Servicio de transporte para Nexo Innovación",
      "ScheduledDate": "2025-03-21T00:00:00"
    },
    {
      "CustomerName": "Soluciones Integrales",
      "From": "Calle Alsina 756, CABA",
      "To": "Av. General Paz 325, CABA",
      "Description": "Servicio de transporte para Soluciones Integrales",
      "ScheduledDate": "2025-03-24T00:00:00"
    },
    {
      "CustomerName": "Horizonte Financiero",
      "From": "Av. de los Incas 978, CABA",
      "To": "Calle Dorrego 436, CABA",
      "Description": "Servicio de transporte para Horizonte Financiero",
      "ScheduledDate": "2025-03-25T00:00:00"
    },
    {
      "CustomerName": "Impulso Creativo",
      "From": "Calle San Juan 190, CABA",
      "To": "Av. Lavalle 547, CABA",
      "Description": "Servicio de transporte para Impulso Creativo",
      "ScheduledDate": "2025-03-26T00:00:00"
    },
    {
      "CustomerName": "Red Empresarial",
      "From": "Av. Roca 212, CABA",
      "To": "Calle Mitre 658, CABA",
      "Description": "Servicio de transporte para Red Empresarial",
      "ScheduledDate": "2025-03-27T00:00:00"
    },
    {
      "CustomerName": "Natura Organics",
      "From": "Calle 25 de Mayo 234, CABA",
      "To": "Av. Córdoba 769, CABA",
      "Description": "Servicio de transporte para Natura Organics",
      "ScheduledDate": "2025-03-28T00:00:00"
    },
    {
      "CustomerName": "Calidad Premium",
      "From": "Av. Juan B. Justo 456, CABA",
      "To": "Calle Independencia 880, CABA",
      "Description": "Servicio de transporte para Calidad Premium",
      "ScheduledDate": "2025-03-31T00:00:00"
    },
    {
      "CustomerName": "EcoVida",
      "From": "Calle Esmeralda 678, CABA",
      "To": "Av. Entre Ríos 991, CABA",
      "Description": "Servicio de transporte para EcoVida",
      "ScheduledDate": "2025-04-01T00:00:00"
    },
    {
      "CustomerName": "Gourmet Delicias",
      "From": "Av. General Paz 890, CABA",
      "To": "Calle Sarmiento 102, CABA",
      "Description": "Servicio de transporte para Gourmet Delicias",
      "ScheduledDate": "2025-04-02T00:00:00"
    },
    {
      "CustomerName": "Sabor y Tradición",
      "From": "Calle San Lorenzo 101, CABA",
      "To": "Av. 25 de Mayo 213, CABA",
      "Description": "Servicio de transporte para Sabor y Tradición",
      "ScheduledDate": "2025-04-03T00:00:00"
    },
    {
      "CustomerName": "Cine & Arte",
      "From": "Av. Paseo Colón 202, CABA",
      "To": "Calle Roque Sáenz Peña 324, CABA",
      "Description": "Servicio de transporte para Cine & Arte",
      "ScheduledDate": "2025-04-04T00:00:00"
    },
    {
      "CustomerName": "Música Latina",
      "From": "Calle Dorrego 303, CABA",
      "To": "Av. Juan B. Justo 435, CABA",
      "Description": "Servicio de transporte para Música Latina",
      "ScheduledDate": "2025-04-07T00:00:00"
    },
    {
      "CustomerName": "Estudios Arco",
      "From": "Av. Córdoba 404, CABA",
      "To": "Calle Corrientes 546, CABA",
      "Description": "Servicio de transporte para Estudios Arco",
      "ScheduledDate": "2025-04-08T00:00:00"
    },
    {
      "CustomerName": "MediaFusión",
      "From": "Calle Mitre 505, CABA",
      "To": "Av. Santa Fe 657, CABA",
      "Description": "Servicio de transporte para MediaFusión",
      "ScheduledDate": "2025-04-09T00:00:00"
    },
    {
      "CustomerName": "Tecnova",
      "From": "Av. Belgrano 606, CABA",
      "To": "Calle Callao 768, CABA",
      "Description": "Servicio de transporte para Tecnova",
      "ScheduledDate": "2025-04-10T00:00:00"
    },
    {
      "CustomerName": "Pixel Creativo",
      "From": "Calle Lavalle 707, CABA",
      "To": "Av. Roca 879, CABA",
      "Description": "Servicio de transporte para Pixel Creativo",
      "ScheduledDate": "2025-04-11T00:00:00"
    },
    {
      "CustomerName": "Digital Minds",
      "From": "Av. Roque Sáenz Peña 808, CABA",
      "To": "Calle Belgrano 980, CABA",
      "Description": "Servicio de transporte para Digital Minds",
      "ScheduledDate": "2025-04-14T00:00:00"
    },
    {
      "CustomerName": "DataWave",
      "From": "Av. Corrientes 1234, CABA",
      "To": "Av. San Martín 1300, CABA",
      "Description": "Servicio de transporte para DataWave",
      "ScheduledDate": "2025-04-15T00:00:00"
    },
    {
      "CustomerName": "InfoTech Solutions",
      "From": "Av. Santa Fe 567, CABA",
      "To": "Calle Juramento 142, CABA",
      "Description": "Servicio de transporte para InfoTech Solutions",
      "ScheduledDate": "2025-04-16T00:00:00"
    },
    {
      "CustomerName": "Innovación Global",
      "From": "Av. Callao 890, CABA",
      "To": "Av. Corrientes 2500, CABA",
      "Description": "Servicio de transporte para Innovación Global",
      "ScheduledDate": "2025-04-17T00:00:00"
    },
    {
      "CustomerName": "Smart Business",
      "From": "Av. Rivadavia 2345, CABA",
      "To": "Calle Bolívar 360, CABA",
      "Description": "Servicio de transporte para Smart Business",
      "ScheduledDate": "2025-04-18T00:00:00"
    },
    {
      "CustomerName": "Alpha Invest",
      "From": "Av. 9 de Julio 101, CABA",
      "To": "Av. Callao 470, CABA",
      "Description": "Servicio de transporte para Alpha Invest",
      "ScheduledDate": "2025-03-21T00:00:00"
    },
    {
      "CustomerName": "Beta Corp",
      "From": "Av. Pueyrredón 456, CABA",
      "To": "Calle Florida 580, CABA",
      "Description": "Servicio de transporte para Beta Corp",
      "ScheduledDate": "2025-03-24T00:00:00"
    },
    {
      "CustomerName": "Gamma Holdings",
      "From": "Calle Florida 789, CABA",
      "To": "Av. Rivadavia 690, CABA",
      "Description": "Servicio de transporte para Gamma Holdings",
      "ScheduledDate": "2025-03-25T00:00:00"
    },
    {
      "CustomerName": "Omega Industries",
      "From": "Av. del Libertador 321, CABA",
      "To": "Calle 9 de Julio 800, CABA",
      "Description": "Servicio de transporte para Omega Industries",
      "ScheduledDate": "2025-03-26T00:00:00"
    },
    {
      "CustomerName": "Sigma Enterprises",
      "From": "Av. de Mayo 654, CABA",
      "To": "Av. Pueyrredón 910, CABA",
      "Description": "Servicio de transporte para Sigma Enterprises",
      "ScheduledDate": "2025-03-27T00:00:00"
    },
    {
      "CustomerName": "Delta Services",
      "From": "Av. Cerviño 987, CABA",
      "To": "Calle Tucumán 102, CABA",
      "Description": "Servicio de transporte para Delta Services",
      "ScheduledDate": "2025-03-28T00:00:00"
    },
    {
      "CustomerName": "Epsilon Group",
      "From": "Av. San Martín 112, CABA",
      "To": "Av. Santa Fe 113, CABA",
      "Description": "Servicio de transporte para Epsilon Group",
      "ScheduledDate": "2025-03-31T00:00:00"
    },
    {
      "CustomerName": "Zeta Solutions",
      "From": "Calle Perú 334, CABA",
      "To": "Calle de la República 124, CABA",
      "Description": "Servicio de transporte para Zeta Solutions",
      "ScheduledDate": "2025-04-01T00:00:00"
    },
    {
      "CustomerName": "Kappa Consulting",
      "From": "Av. Belgrano 556, CABA",
      "To": "Av. de Mayo 235, CABA",
      "Description": "Servicio de transporte para Kappa Consulting",
      "ScheduledDate": "2025-04-02T00:00:00"
    },
    {
      "CustomerName": "Lambda Ventures",
      "From": "Calle Sarmiento 778, CABA",
      "To": "Calle Esmeralda 346, CABA",
      "Description": "Servicio de transporte para Lambda Ventures",
      "ScheduledDate": "2025-04-03T00:00:00"
    },
    {
      "CustomerName": "Nu Capital",
      "From": "Av. Independencia 990, CABA",
      "To": "Av. Libertador 457, CABA",
      "Description": "Servicio de transporte para Nu Capital",
      "ScheduledDate": "2025-04-04T00:00:00"
    },
    {
      "CustomerName": "Omicron Technologies",
      "From": "Calle Bolívar 221, CABA",
      "To": "Calle Belgrano 568, CABA",
      "Description": "Servicio de transporte para Omicron Technologies",
      "ScheduledDate": "2025-04-07T00:00:00"
    },
    {
      "CustomerName": "Pi Electronics",
      "From": "Av. Entre Ríos 443, CABA",
      "To": "Av. del Libertador 679, CABA",
      "Description": "Servicio de transporte para Pi Electronics",
      "ScheduledDate": "2025-04-08T00:00:00"
    },
    {
      "CustomerName": "Rho Retail",
      "From": "Av. Lavalle 665, CABA",
      "To": "Calle Alsina 780, CABA",
      "Description": "Servicio de transporte para Rho Retail",
      "ScheduledDate": "2025-04-09T00:00:00"
    },
    {
      "CustomerName": "Tau Foods",
      "From": "Calle Moreno 887, CABA",
      "To": "Av. Congreso 891, CABA",
      "Description": "Servicio de transporte para Tau Foods",
      "ScheduledDate": "2025-04-10T00:00:00"
    },
    {
      "CustomerName": "Upsilon Pharma",
      "From": "Av. Maipú 109, CABA",
      "To": "Calle San Juan 902, CABA",
      "Description": "Servicio de transporte para Upsilon Pharma",
      "ScheduledDate": "2025-04-11T00:00:00"
    },
    {
      "CustomerName": "Phi Beverages",
      "From": "Calle Tucumán 312, CABA",
      "To": "Av. Maipú 103, CABA",
      "Description": "Servicio de transporte para Phi Beverages",
      "ScheduledDate": "2025-04-14T00:00:00"
    },
    {
      "CustomerName": "Chi Textiles",
      "From": "Av. Congreso 534, CABA",
      "To": "Calle San Lorenzo 214, CABA",
      "Description": "Servicio de transporte para Chi Textiles",
      "ScheduledDate": "2025-04-15T00:00:00"
    },
    {
      "CustomerName": "Psi Chemicals",
      "From": "Calle Alsina 756, CABA",
      "To": "Av. General Paz 325, CABA",
      "Description": "Servicio de transporte para Psi Chemicals",
      "ScheduledDate": "2025-04-16T00:00:00"
    },
    {
      "CustomerName": "Omega Materials",
      "From": "Av. de los Incas 978, CABA",
      "To": "Calle Dorrego 436, CABA",
      "Description": "Servicio de transporte para Omega Materials",
      "ScheduledDate": "2025-04-17T00:00:00"
    },
    {
      "CustomerName": "Nueva Imagen",
      "From": "Calle San Juan 190, CABA",
      "To": "Av. Lavalle 547, CABA",
      "Description": "Servicio de transporte para Nueva Imagen",
      "ScheduledDate": "2025-04-18T00:00:00"
    },
    {
      "CustomerName": "Brillante Ideas",
      "From": "Av. Roca 212, CABA",
      "To": "Calle Mitre 658, CABA",
      "Description": "Servicio de transporte para Brillante Ideas",
      "ScheduledDate": "2025-03-21T00:00:00"
    },
    {
      "CustomerName": "Cumbre Creativa",
      "From": "Calle 25 de Mayo 234, CABA",
      "To": "Av. Córdoba 769, CABA",
      "Description": "Servicio de transporte para Cumbre Creativa",
      "ScheduledDate": "2025-03-24T00:00:00"
    },
    {
      "CustomerName": "Faro Empresarial",
      "From": "Av. Juan B. Justo 456, CABA",
      "To": "Calle Independencia 880, CABA",
      "Description": "Servicio de transporte para Faro Empresarial",
      "ScheduledDate": "2025-03-25T00:00:00"
    },
    {
      "CustomerName": "Punto de Encuentro",
      "From": "Calle Esmeralda 678, CABA",
      "To": "Av. Entre Ríos 991, CABA",
      "Description": "Servicio de transporte para Punto de Encuentro",
      "ScheduledDate": "2025-03-26T00:00:00"
    },
    {
      "CustomerName": "Clave Urbana",
      "From": "Av. General Paz 890, CABA",
      "To": "Calle Sarmiento 102, CABA",
      "Description": "Servicio de transporte para Clave Urbana",
      "ScheduledDate": "2025-03-27T00:00:00"
    },
    {
      "CustomerName": "Estrella del Norte",
      "From": "Calle San Lorenzo 101, CABA",
      "To": "Av. 25 de Mayo 213, CABA",
      "Description": "Servicio de transporte para Estrella del Norte",
      "ScheduledDate": "2025-03-28T00:00:00"
    },
    {
      "CustomerName": "Aurora Global",
      "From": "Av. Paseo Colón 202, CABA",
      "To": "Calle Roque Sáenz Peña 324, CABA",
      "Description": "Servicio de transporte para Aurora Global",
      "ScheduledDate": "2025-03-31T00:00:00"
    },
    {
      "CustomerName": "Sol Naciente",
      "From": "Calle Dorrego 303, CABA",
      "To": "Av. Juan B. Justo 435, CABA",
      "Description": "Servicio de transporte para Sol Naciente",
      "ScheduledDate": "2025-04-01T00:00:00"
    },
    {
      "CustomerName": "Luz de Plata",
      "From": "Av. Córdoba 404, CABA",
      "To": "Calle Corrientes 546, CABA",
      "Description": "Servicio de transporte para Luz de Plata",
      "ScheduledDate": "2025-04-02T00:00:00"
    },
    {
      "CustomerName": "Manantial Natural",
      "From": "Calle Mitre 505, CABA",
      "To": "Av. Santa Fe 657, CABA",
      "Description": "Servicio de transporte para Manantial Natural",
      "ScheduledDate": "2025-04-03T00:00:00"
    },
    {
      "CustomerName": "Fuente de Vida",
      "From": "Av. Belgrano 606, CABA",
      "To": "Calle Callao 768, CABA",
      "Description": "Servicio de transporte para Fuente de Vida",
      "ScheduledDate": "2025-04-04T00:00:00"
    },
    {
      "CustomerName": "Corazón Argentino",
      "From": "Calle Lavalle 707, CABA",
      "To": "Av. Roca 879, CABA",
      "Description": "Servicio de transporte para Corazón Argentino",
      "ScheduledDate": "2025-04-07T00:00:00"
    },
    {
      "CustomerName": "Patrimonio Vivo",
      "From": "Av. Roque Sáenz Peña 808, CABA",
      "To": "Calle Belgrano 980, CABA",
      "Description": "Servicio de transporte para Patrimonio Vivo",
      "ScheduledDate": "2025-04-08T00:00:00"
    },
    {
      "CustomerName": "Raíces y Alas",
      "From": "Av. Corrientes 1234, CABA",
      "To": "Av. San Martín 1300, CABA",
      "Description": "Servicio de transporte para Raíces y Alas",
      "ScheduledDate": "2025-04-09T00:00:00"
    },
    {
      "CustomerName": "Sueño Dorado",
      "From": "Av. Santa Fe 567, CABA",
      "To": "Calle Juramento 142, CABA",
      "Description": "Servicio de transporte para Sueño Dorado",
      "ScheduledDate": "2025-04-10T00:00:00"
    },
    {
      "CustomerName": "Horizonte Claro",
      "From": "Av. Callao 890, CABA",
      "To": "Av. Corrientes 2500, CABA",
      "Description": "Servicio de transporte para Horizonte Claro",
      "ScheduledDate": "2025-04-11T00:00:00"
    },
    {
      "CustomerName": "Visión Serena",
      "From": "Av. Rivadavia 2345, CABA",
      "To": "Calle Bolívar 360, CABA",
      "Description": "Servicio de transporte para Visión Serena",
      "ScheduledDate": "2025-04-14T00:00:00"
    },
    {
      "CustomerName": "Imaginarium",
      "From": "Av. 9 de Julio 101, CABA",
      "To": "Calle Juramento 142, CABA",
      "Description": "Servicio de transporte para Imaginarium",
      "ScheduledDate": "2025-04-15T00:00:00"
    },
    {
      "CustomerName": "Ideas Frescas",
      "From": "Av. Pueyrredón 456, CABA",
      "To": "Calle Florida 580, CABA",
      "Description": "Servicio de transporte para Ideas Frescas",
      "ScheduledDate": "2025-04-16T00:00:00"
    },
    {
      "CustomerName": "Espacio Innovador",
      "From": "Calle Florida 789, CABA",
      "To": "Av. Rivadavia 690, CABA",
      "Description": "Servicio de transporte para Espacio Innovador",
      "ScheduledDate": "2025-04-17T00:00:00"
    },
    {
      "CustomerName": "Planeta Verde",
      "From": "Av. del Libertador 321, CABA",
      "To": "Calle 9 de Julio 800, CABA",
      "Description": "Servicio de transporte para Planeta Verde",
      "ScheduledDate": "2025-04-18T00:00:00"
    }
  ]


